{
  "_fv": 18,
  "_type": "tool",
  "definition": {
    "renderType": 0,
    "texture": "carnelian_shard_hoe",
    "customModelName": "Normal",
    "name": "Carnelian Shard Hoe",
    "specialInfo": [],
    "creativeTab": {
      "value": "CUSTOM:MagicCraft"
    },
    "toolType": "Hoe",
    "harvestLevel": 2,
    "efficiency": 6.0,
    "attackSpeed": 1.0,
    "enchantability": 14,
    "damageVsEntity": 3.0,
    "usageCount": 512,
    "blocksAffected": [],
    "hasGlow": false,
    "repairItems": [
      {
        "value": "CUSTOM:CarnelianShard"
      },
      {
        "value": "CUSTOM:CarnelianCrystal"
      }
    ],
    "immuneToFire": false,
    "stayInGridWhenCrafting": false,
    "damageOnCrafting": false
  }
}