{
  "_fv": 18,
  "_type": "achievement",
  "definition": {
    "achievementName": "Crystallized",
    "achievementDescription": "Get your first Carnelian Crystal! There are rumors of one even harder to get...",
    "achievementIcon": {
      "value": "CUSTOM:CarnelianCrystal"
    },
    "background": "Default",
    "disableDisplay": false,
    "showPopup": true,
    "announceToChat": true,
    "hideIfNotCompleted": true,
    "rewardLoot": [],
    "rewardRecipes": [
      "CarnelianBlockRecipe",
      "CondensedCarnelianRecipe",
      "CarnelianCrystalSwordRecipe",
      "CarnelianCrystalPickaxeRecipe",
      "CarnelianCrystalShovelRecipe",
      "CarnelianCrystalAxeRecipe",
      "CarnelianCrystalHoeRecipe",
      "FlameGemRecipe",
      "FrostGemRecipe",
      "NatureGemRecipe",
      "FlameWandRecipe",
      "FrostWandRecipe",
      "NatureWandRecipe",
      "CarnelianCrystalHelmetRecipe",
      "CarnelianCrystalChestplateRecipe",
      "CarnelianCrystalLeggingsRecipe",
      "CarnelianCrystalBootsRecipe"
    ],
    "rewardFunction": "No function",
    "rewardXP": 1,
    "achievementType": "task",
    "parent": {
      "value": "CUSTOM:FirstCarnelian"
    },
    "triggerxml": "<xml xmlns=\"https://developers.google.com/blockly/xml\"><block type=\"item_in_inventory\" x=\"77\" y=\"123\"><value name=\"amount_l\"><block type=\"math_number\"><field name=\"NUM\">1</field></block></value><value name=\"amount_h\"><block type=\"math_number\"><field name=\"NUM\">2368</field></block></value><value name=\"item\"><block type=\"mcitem_all\"><field name=\"value\">CUSTOM:CarnelianCrystal</field></block></value><next><block type=\"advancement_trigger\" deletable=\"false\"></block></next></block></xml>"
  }
}